[
  {
    "start": "0:07",
    "end": "0:10",
    "text": "[Music]"
  },
  {
    "start": "0:10",
    "end": "0:17",
    "text": "I like ice cream."
  },
  {
    "start": "0:17",
    "end": "0:22",
    "text": "Grandma likes ice cream. M"
  },
  {
    "start": "0:22",
    "end": "0:25",
    "text": "[Music]"
  },
  {
    "start": "0:25",
    "end": "0:27",
    "text": "Grandpa likes ice cream."
  },
  {
    "start": "0:27",
    "end": "0:30",
    "text": "M"
  },
  {
    "start": "0:30",
    "end": "0:33",
    "text": "[Music]"
  },
  {
    "start": "0:33",
    "end": "0:36",
    "text": "Dad likes ice cream."
  },
  {
    "start": "0:36",
    "end": "0:38",
    "text": "M"
  },
  {
    "start": "0:38",
    "end": "0:41",
    "text": "[Music]"
  },
  {
    "start": "0:41",
    "end": "0:48",
    "text": "Mom likes ice cream. M"
  },
  {
    "start": "0:48",
    "end": "0:51",
    "text": "Uncle Ted likes ice cream."
  },
  {
    "start": "0:51",
    "end": "0:54",
    "text": "M"
  },
  {
    "start": "0:54",
    "end": "0:56",
    "text": "[Music]"
  },
  {
    "start": "0:56",
    "end": "1:00",
    "text": "My baby sister likes ice cream."
  },
  {
    "start": "1:00",
    "end": "1:02",
    "text": "Yummy."
  },
  {
    "start": "1:02",
    "end": "1:05",
    "text": "[Music]"
  },
  {
    "start": "1:05",
    "end": "1:08",
    "text": "My brother likes ice cream."
  },
  {
    "start": "1:08",
    "end": "1:10",
    "text": "Yummy."
  },
  {
    "start": "1:10",
    "end": "1:11",
    "text": "[Music]"
  },
  {
    "start": "1:11",
    "end": "1:15",
    "text": "I like ice cream, too. Yummy."
  },
  {
    "start": "1:15",
    "end": "1:20",
    "text": "[Music]"
  }
]